milesConverter/__init__.py
milesConverter/km2miles.py
milesConverter-1.2.0.dist-info/LICENSE
milesConverter-1.2.0.dist-info/METADATA
milesConverter-1.2.0.dist-info/WHEEL
milesConverter-1.2.0.dist-info/top_level.txt
milesConverter-1.2.0.dist-info/RECORD
