Metadata-Version: 2.1
Name: milesConverter
Version: 1.2.0
Summary: Convert KMs to Miles
Author-email: Gourav Bais <gouravbais08@gmail.com>
License: MIT License        
Keywords: converter,miles,kms
Classifier: License :: OSI Approved :: MIT License
Classifier: Programming Language :: Python
Classifier: Programming Language :: Python :: 3
Classifier: Operating System :: MacOS :: MacOS X
Classifier: Operating System :: Microsoft :: Windows
Classifier: Intended Audience :: Education
Requires-Python: >=3.9
License-File: LICENSE
Requires-Dist: numpy (>=1.20.3)
